{
  "warframe": {
    "settings": {
      "_comments": {
        "game_deadzone": "Set to 0 since right-stick deadzone is disabled in-game for true 1:1 aiming.",
        "max_velocity": "Cap for mouse velocity. Need a fast flick while still maintaining responsiveness for fine control.",
        "curve_exponent": "Low to make it feel more natural and less sticky.",
        "input_smoothing": "Raw mickey smoothing.",
        "output_smoothing": "0.3 is a good default.",
        "noise_filter_ms": "1ms timeout to stop drift when your hand is entirely still to make it snappy.",
        "sens_x": "x-axis sensitivity.",
        "sens_y": "y-axis sensitivity."
      },
      "game_deadzone": 0,
      "max_velocity": 30000.0,
      "curve_exponent": 0.45,
      "input_smoothing": 0.4,
      "output_smoothing": 0.4,
      "noise_filter_ms": 3.0,
      "sens_x": 180,
      "sens_y": 180
    },
    "key_profile": {
      "0x01": "XUSB_GAMEPAD_START",
      "0x06": "XUSB_GAMEPAD_DPAD_LEFT",
      "0x0F": "XUSB_GAMEPAD_RIGHT_THUMB",
      "0x10": "XUSB_GAMEPAD_DPAD_UP",
      "0x12": "XUSB_GAMEPAD_X",
      "0x1D": "XUSB_GAMEPAD_LEFT_THUMB",
      "0x21": "XUSB_GAMEPAD_B",
      "0x2A": "XUSB_GAMEPAD_LEFT_SHOULDER",
      "0x2C": "XUSB_GAMEPAD_DPAD_DOWN",
      "0x39": "XUSB_GAMEPAD_RIGHT_SHOULDER",
      "0x3B": "XUSB_GAMEPAD_BACK"
    },
    "combos": {
      "0x02": ["XUSB_GAMEPAD_DPAD_RIGHT", "XUSB_GAMEPAD_A"],
      "0x03": ["XUSB_GAMEPAD_DPAD_RIGHT", "XUSB_GAMEPAD_X"],
      "0x04": ["XUSB_GAMEPAD_DPAD_RIGHT", "XUSB_GAMEPAD_B"],
      "0x05": ["XUSB_GAMEPAD_DPAD_RIGHT", "XUSB_GAMEPAD_Y"]
    },
    "mouse_buttons": {
      "LEFT_DOWN": "RIGHT_TRIGGER",
      "LEFT_UP": "RIGHT_TRIGGER",
      "RIGHT_DOWN": "LEFT_TRIGGER",
      "RIGHT_UP": "LEFT_TRIGGER",
      "MIDDLE_DOWN": "XUSB_GAMEPAD_A",
      "MIDDLE_UP": "XUSB_GAMEPAD_A",
      "X1_DOWN": "XUSB_GAMEPAD_Y",
      "X1_UP": "XUSB_GAMEPAD_Y"
    },
    "movement": {
      "W": "0x11",
      "A": "0x1E",
      "S": "0x1F",
      "D": "0x20"
    }
  }
}
